<?xml version="1.0" encoding="UTF-8"?>
<!DOCTYPE hibernate-mapping PUBLIC "-//Hibernate/Hibernate Mapping DTD 3.0//EN" "http://www.hibernate.org/dtd/hibernate-mapping-3.0.dtd">
<!-- Generated 30-may-2015 11:21:15 by Hibernate Tools 4.3.1 -->
<hibernate-mapping>
  <class name="com.ues.model.Cotizacion" optimistic-lock="version" schema="INVENTARIO" table="COTIZACION">
    <id name="idCotizacion" type="int">
      <column name="ID_COTIZACION" precision="6" scale="0"/>
      <generator class="assigned"/>
    </id>
    <many-to-one class="com.ues.model.Proveedor" fetch="select" name="proveedor">
      <column name="ID_PROVEEDOR" not-null="true" precision="6" scale="0"/>
    </many-to-one>
    <many-to-one class="com.ues.model.Pedido" fetch="select" name="pedido">
      <column name="ID_PEDIDO" not-null="true" precision="6" scale="0"/>
    </many-to-one>
    <property name="estadoCot" type="big_decimal">
      <column name="ESTADO_COT" not-null="true" precision="22" scale="0"/>
    </property>
    <set fetch="select" inverse="true" lazy="true" name="ordenDeCompras" table="ORDEN_DE_COMPRA">
      <key>
        <column name="ID_COTIZACION" not-null="true" precision="6" scale="0"/>
      </key>
      <one-to-many class="com.ues.model.OrdenDeCompra"/>
    </set>
  </class>
</hibernate-mapping>
